notebook_separate_output/__init__.py
notebook_separate_output-1.0.dist-info/METADATA
notebook_separate_output-1.0.dist-info/RECORD
notebook_separate_output-1.0.dist-info/WHEEL
notebook_separate_output-1.0.dist-info/top_level.txt
