Metadata-Version: 2.1
Name: notebook-separate-output
Version: 1.0
Summary: Jupyter Notebook extension to redirect cell output to separate text file.
Home-page: https://gitlab.com/alelec/notebook_separate_output
Author: Andrew Leech
Author-email: andrew.leech@planetinnovation.com.au
License: UNKNOWN
Platform: UNKNOWN
